circuits_py/__init__.py
circuits_py/helpers.py
circuits_py/logic.py
circuits_py/state.py
circuits_py-0.1.1.dist-info/LICENSE
circuits_py-0.1.1.dist-info/METADATA
circuits_py-0.1.1.dist-info/WHEEL
circuits_py-0.1.1.dist-info/top_level.txt
circuits_py-0.1.1.dist-info/RECORD
