Metadata-Version: 2.1
Name: circuits-py
Version: 0.1.1
Summary: A python package for creating logic circuits.
Author: 0xA4
License: UNKNOWN
Project-URL: usage examples, https://gist.github.com/Himaghna-Senarath/6a5fda03bc9bb73142d3ead2685f1e29
Keywords: 'circuits logic gates'
Platform: UNKNOWN
Classifier: Programming Language :: Python :: 3
Classifier: License :: OSI Approved :: The Unlicense (Unlicense)
Classifier: Operating System :: OS Independent
Requires-Python: >=3.6
License-File: LICENSE
